azol/__init__.py
azol/constants.py
azol/caches/__init__.py
azol/caches/azol_cache.py
azol/caches/in_memory_token_cache.py
azol/caches/local_token_cache.py
azol/clients/__init__.py
azol/clients/arm_client.py
azol/clients/azure_devops_client.py
azol/clients/datafactory_client.py
azol/clients/devops_agent_client.py
azol/clients/graph_client.py
azol/clients/key_vault_client.py
azol/clients/kudu_client.py
azol/clients/oauth_http_client.py
azol/credentials/__init__.py
azol/credentials/access_token.py
azol/credentials/application_object.py
azol/credentials/azure_devops_agent_key.py
azol/credentials/azure_devops_pipeline_workload_federation_credential.py
azol/credentials/credential.py
azol/credentials/entraid_credential.py
azol/credentials/service_principal.py
azol/credentials/user.py
azol/models/__init__.py
azol/models/devops_rsa_parameters.py
azol/models/ests_cookie.py
azol/models/generic_resource.py
azol/models/sp_login_init_model.py
azol/providers/__init__.py
azol/providers/file_secret_provider.py
azol/providers/key_vault_secret_provider.py
azol/resources/__init__.py
azol/resources/graph_delegated_permissions.py
azol/resources/graph_permissions_map.py
azol/resources/rbac_roles.py
azol/services/__init__.py
azol/services/token_service.py
azol/services/token_service_helpers.py
azol/utils/__init__.py
azol/utils/auth_utils.py
azol/utils/utils.py
azol/utils/local/__init__.py
azol/utils/local/azuredevops/__init__.py
azol/utils/local/azuredevops/azure_devops_utils.py
azol/utils/local/windows/__init__.py
azol/utils/local/windows/windows_utils.py
azol-0.5.2.dist-info/licenses/LICENSE
azol-0.5.2.dist-info/METADATA
azol-0.5.2.dist-info/WHEEL
azol-0.5.2.dist-info/top_level.txt
azol-0.5.2.dist-info/RECORD
