Metadata-Version: 2.4
Name: azol
Version: 0.5.2
Summary: A python-based pentesting library for Azure and Entra ID
Home-page: https://github.com/cdburkard/azol
Author: Cody Burkard
License-File: LICENSE
Requires-Dist: requests==2.31.0
Requires-Dist: dataclasses==0.6
Requires-Dist: cryptography
Dynamic: author
Dynamic: description
Dynamic: description-content-type
Dynamic: home-page
Dynamic: license-file
Dynamic: requires-dist
Dynamic: summary
